verilog/minc.v
module minc (
    input wire CLK,
    input wire nRESET,
    output wire [15:0] pc_out,
    output wire [7:0] acc_out
);

    wire [7:0] data;
    reg  [7:0] pc;

    reg [7:0] accumulator;

    reg [7:0] rom [0:255];
    initial $readmemh("program.hex", rom);

    assign pc_out = pc;
    assign acc_out = accumulator;

    always @(posedge CLK or negedge nRESET) begin
        if (!nRESET) begin
            pc <= 8'h0;
            accumulator <= 8'h0;
        end else begin
            accumulator <= rom[pc[7:0]];
            pc <= pc + 1;
        end
    end

endmodule

verilog/minc_tb.v
`timescale 1ns/1ps

module minc_tb;

    reg CLK;
    reg nRESET;
    wire [15:0] pc_out;
    wire [7:0] acc_out;
    integer i;

    // Instantiate the DUT
    minc uut (
        .CLK(CLK),
        .nRESET(nRESET),
        .pc_out(pc_out),
        .acc_out(acc_out)
    );

    // Clock generator: 10 ns period
    initial begin
        CLK = 0;
        forever #5 CLK = ~CLK;
    end

    // Reset sequence
    initial begin
        nRESET = 0;
        #20;
        nRESET = 1;
    end

    // Waveform dump for Icarus / GTKWave
    initial begin
        $dumpfile("minc_tb.vcd");
        $dumpvars(0, minc_tb);
    end

    // Simple monitor and stop after a number of cycles
    initial begin
        $display("TIME\tPC\tACC");
        // wait for reset to deassert
        @(posedge nRESET);
        // wait a little after reset release
        #1;
        for (i = 0; i < 64; i = i + 1) begin
            @(posedge CLK);
            $display("%0t\t%0h\t%0h", $time, pc_out, acc_out);
        end
        #10;
        $finish;
    end

endmodule

verilog/minc_tb.vcd
$date
	Tue Oct 28 17:20:53 2025
$end
$version
	Icarus Verilog
$end
$timescale
	1ps
$end
$scope module minc_tb $end
$var wire 16 ! pc_out [15:0] $end
$var wire 8 " acc_out [7:0] $end
$var reg 1 # CLK $end
$var reg 1 $ nRESET $end
$var integer 32 % i [31:0] $end
$scope module uut $end
$var wire 1 # CLK $end
$var wire 8 & acc_out [7:0] $end
$var wire 1 $ nRESET $end
$var wire 16 ' pc_out [15:0] $end
$var reg 8 ( accumulator [7:0] $end
$var reg 8 ) pc [7:0] $end
$upscope $end
$upscope $end
$enddefinitions $end
$comment Show the parameter values. $end
$dumpall
$end
#0
$dumpvars
b0 )
b0 (
b0 '
b0 &
bx %
0$
0#
b0 "
b0 !
$end
#5000
1#
#10000
0#
#15000
1#
#20000
0#
1$
#21000
b0 %
#25000
b1 !
b1 '
b1 )
b1 %
1#
#30000
0#
#35000
b10 !
b10 '
b10 )
b10001 "
b10001 &
b10001 (
b10 %
1#
#40000
0#
#45000
b11 !
b11 '
b11 )
b100010 "
b100010 &
b100010 (
b11 %
1#
#50000
0#
#55000
b100 !
b100 '
b100 )
b110011 "
b110011 &
b110011 (
b100 %
1#
#60000
0#
#65000
b101 !
b101 '
b101 )
b1000100 "
b1000100 &
b1000100 (
b101 %
1#
#70000
0#
#75000
b110 !
b110 '
b110 )
b1010101 "
b1010101 &
b1010101 (
b110 %
1#
#80000
0#
#85000
b111 !
b111 '
b111 )
b1100110 "
b1100110 &
b1100110 (
b111 %
1#
#90000
0#
#95000
b1000 !
b1000 '
b1000 )
b1110111 "
b1110111 &
b1110111 (
b1000 %
1#
#100000
0#
#105000
b1001 !
b1001 '
b1001 )
b10001000 "
b10001000 &
b10001000 (
b1001 %
1#
#110000
0#
#115000
b1010 !
b1010 '
b1010 )
b10011001 "
b10011001 &
b10011001 (
b1010 %
1#
#120000
0#
#125000
b1011 !
b1011 '
b1011 )
b10101010 "
b10101010 &
b10101010 (
b1011 %
1#
#130000
0#
#135000
b1100 !
b1100 '
b1100 )
b10111011 "
b10111011 &
b10111011 (
b1100 %
1#
#140000
0#
#145000
b1101 !
b1101 '
b1101 )
b11001100 "
b11001100 &
b11001100 (
b1101 %
1#
#150000
0#
#155000
b1110 !
b1110 '
b1110 )
b11011101 "
b11011101 &
b11011101 (
b1110 %
1#
#160000
0#
#165000
b1111 !
b1111 '
b1111 )
b11101110 "
b11101110 &
b11101110 (
b1111 %
1#
#170000
0#
#175000
b10000 !
b10000 '
b10000 )
b11111111 "
b11111111 &
b11111111 (
b10000 %
1#
#180000
0#
#185000
b10001 !
b10001 '
b10001 )
b1 "
b1 &
b1 (
b10001 %
1#
#190000
0#
#195000
b10010 !
b10010 '
b10010 )
b10 "
b10 &
b10 (
b10010 %
1#
#200000
0#
#205000
b10011 !
b10011 '
b10011 )
b11 "
b11 &
b11 (
b10011 %
1#
#210000
0#
#215000
b10100 !
b10100 '
b10100 )
b100 "
b100 &
b100 (
b10100 %
1#
#220000
0#
#225000
b10101 !
b10101 '
b10101 )
b101 "
b101 &
b101 (
b10101 %
1#
#230000
0#
#235000
b10110 !
b10110 '
b10110 )
b110 "
b110 &
b110 (
b10110 %
1#
#240000
0#
#245000
b10111 !
b10111 '
b10111 )
b111 "
b111 &
b111 (
b10111 %
1#
#250000
0#
#255000
b11000 !
b11000 '
b11000 )
b1000 "
b1000 &
b1000 (
b11000 %
1#
#260000
0#
#265000
b11001 !
b11001 '
b11001 )
b1001 "
b1001 &
b1001 (
b11001 %
1#
#270000
0#
#275000
b11010 !
b11010 '
b11010 )
b1010 "
b1010 &
b1010 (
b11010 %
1#
#280000
0#
#285000
b11011 !
b11011 '
b11011 )
b1011 "
b1011 &
b1011 (
b11011 %
1#
#290000
0#
#295000
b11100 !
b11100 '
b11100 )
b1100 "
b1100 &
b1100 (
b11100 %
1#
#300000
0#
#305000
b11101 !
b11101 '
b11101 )
b1101 "
b1101 &
b1101 (
b11101 %
1#
#310000
0#
#315000
b11110 !
b11110 '
b11110 )
b1110 "
b1110 &
b1110 (
b11110 %
1#
#320000
0#
#325000
b11111 !
b11111 '
b11111 )
b1111 "
b1111 &
b1111 (
b11111 %
1#
#330000
0#
#335000
b100000 !
b100000 '
b100000 )
b10000 "
b10000 &
b10000 (
b100000 %
1#
#340000
0#
#345000
b100001 !
b100001 '
b100001 )
b10001 "
b10001 &
b10001 (
b100001 %
1#
#350000
0#
#355000
b100010 !
b100010 '
b100010 )
bx "
bx &
bx (
b100010 %
1#
#360000
0#
#365000
b100011 !
b100011 '
b100011 )
b100011 %
1#
#370000
0#
#375000
b100100 !
b100100 '
b100100 )
b100100 %
1#
#380000
0#
#385000
b100101 !
b100101 '
b100101 )
b100101 %
1#
#390000
0#
#395000
b100110 !
b100110 '
b100110 )
b100110 %
1#
#400000
0#
#405000
b100111 !
b100111 '
b100111 )
b100111 %
1#
#410000
0#
#415000
b101000 !
b101000 '
b101000 )
b101000 %
1#
#420000
0#
#425000
b101001 !
b101001 '
b101001 )
b101001 %
1#
#430000
0#
#435000
b101010 !
b101010 '
b101010 )
b101010 %
1#
#440000
0#
#445000
b101011 !
b101011 '
b101011 )
b101011 %
1#
#450000
0#
#455000
b101100 !
b101100 '
b101100 )
b101100 %
1#
#460000
0#
#465000
b101101 !
b101101 '
b101101 )
b101101 %
1#
#470000
0#
#475000
b101110 !
b101110 '
b101110 )
b101110 %
1#
#480000
0#
#485000
b101111 !
b101111 '
b101111 )
b101111 %
1#
#490000
0#
#495000
b110000 !
b110000 '
b110000 )
b110000 %
1#
#500000
0#
#505000
b110001 !
b110001 '
b110001 )
b110001 %
1#
#510000
0#
#515000
b110010 !
b110010 '
b110010 )
b110010 %
1#
#520000
0#
#525000
b110011 !
b110011 '
b110011 )
b110011 %
1#
#530000
0#
#535000
b110100 !
b110100 '
b110100 )
b110100 %
1#
#540000
0#
#545000
b110101 !
b110101 '
b110101 )
b110101 %
1#
#550000
0#
#555000
b110110 !
b110110 '
b110110 )
b110110 %
1#
#560000
0#
#565000
b110111 !
b110111 '
b110111 )
b110111 %
1#
#570000
0#
#575000
b111000 !
b111000 '
b111000 )
b111000 %
1#
#580000
0#
#585000
b111001 !
b111001 '
b111001 )
b111001 %
1#
#590000
0#
#595000
b111010 !
b111010 '
b111010 )
b111010 %
1#
#600000
0#
#605000
b111011 !
b111011 '
b111011 )
b111011 %
1#
#610000
0#
#615000
b111100 !
b111100 '
b111100 )
b111100 %
1#
#620000
0#
#625000
b111101 !
b111101 '
b111101 )
b111101 %
1#
#630000
0#
#635000
b111110 !
b111110 '
b111110 )
b111110 %
1#
#640000
0#
#645000
b111111 !
b111111 '
b111111 )
b111111 %
1#
#650000
0#
#655000
b1000000 !
b1000000 '
b1000000 )
b1000000 %
1#
#660000
0#
#665000
b1000001 !
b1000001 '
b1000001 )
1#
